{
    "bg": "https://i2.wp.com/css-tricks.com/wp-content/uploads/2017/06/css-is-awesome-scaled.jpg?resize=1536%2C1208&ssl=1",
    "title": "Quiz CSS da Alura",
    "description": "Teste os seus conhecimentos sobre CSS e vamos ver quantos layouts você vai deixar de quebrar",
    "questions": [
      {
        "image": "https://media.giphy.com/media/MUlmRFnTQxwJ2/giphy.gif",
        "title": "Quando foi lançado o primeiro filme do Homem de Ferro?",
        "description": "Essa é pra aquecer",
        "answer": 3,
        "alternatives": [
          "2005",
          "2006",
          "2007",
          "2008"
        ]
      },
      {
        "image": "https://media1.tenor.com/images/ee70f95440b0222013e7d6087226ec12/tenor.gif?itemid=17755537",
        "title": "Quem foi o vilão do filme Os Vingadores?",
        "description": "Essa é fácil hein!!",
        "answer": 2,
        "alternatives": [
          "Thanos",
          "Galactus",
          "Loki",
          "Doutor Destino"
        ]
      }
    ],
    "external": [
      ""
    ],
    "theme": {
      "colors": {
        "primary": "#3F51B5",
        "secondary": "#E91E63",
        "mainBg": "#171B35",
        "contrastText": "#FFFFFF",
        "wrong": "#FF5722",
        "success": "#4CAF50"
      },
      "borderRadius": "4px"
    }
  }